prtg_pyprobe/__init__.py
prtg_pyprobe/run.py
prtg_pyprobe/communication/__init__.py
prtg_pyprobe/communication/communication_http_api.py
prtg_pyprobe/monitoring/__init__.py
prtg_pyprobe/monitoring/monitoring.py
prtg_pyprobe/sensors/__init__.py
prtg_pyprobe/sensors/helpers.py
prtg_pyprobe/sensors/sensor.py
prtg_pyprobe/sensors/sensor_cpuload.py
prtg_pyprobe/sensors/sensor_dns.py
prtg_pyprobe/sensors/sensor_dns_reverse.py
prtg_pyprobe/sensors/sensor_external_ip.py
prtg_pyprobe/sensors/sensor_http.py
prtg_pyprobe/sensors/sensor_http_rest.py
prtg_pyprobe/sensors/sensor_ping.py
prtg_pyprobe/sensors/sensor_port.py
prtg_pyprobe/sensors/sensor_probe_diskspace.py
prtg_pyprobe/sensors/sensor_probe_health.py
prtg_pyprobe/sensors/sensor_probe_memory.py
prtg_pyprobe/sensors/sensor_probe_temperature.py
prtg_pyprobe/sensors/sensor_prometheus_exporter.py
prtg_pyprobe/sensors/sensor_s3_bucket_total.py
prtg_pyprobe/sensors/sensor_script.py
prtg_pyprobe/sensors/sensor_snmp_cpuload.py
prtg_pyprobe/sensors/sensor_snmp_custom.py
prtg_pyprobe/sensors/sensor_snmp_traffic.py
prtg_pyprobe/sensors/sensor_traffic.py
prtg_pyprobe/utils/__init__.py
prtg_pyprobe/utils/cli.py
prtg_pyprobe/utils/config.py
prtg_pyprobe/utils/defaults.py
prtg_pyprobe/utils/logging.py
prtg_pyprobe/utils/pyprobe.service
prtg_pyprobe/utils/sensor_loader.py
prtg_pyprobe/utils/validators.py
tests/__init__.py
tests/conftest.py
tests/test_run.py
prtg_pyprobe-1.1.4.dist-info/LICENSE.txt
prtg_pyprobe-1.1.4.dist-info/METADATA
prtg_pyprobe-1.1.4.dist-info/WHEEL
prtg_pyprobe-1.1.4.dist-info/entry_points.txt
prtg_pyprobe-1.1.4.dist-info/top_level.txt
prtg_pyprobe-1.1.4.dist-info/RECORD
