Metadata-Version: 2.1
Name: prtg-pyprobe
Version: 1.1.4
Summary: Python Probe for PRTG Network Monitor
Home-page: UNKNOWN
License: BSD-3-Clause
Project-URL: Documentation, https://paessler-labs.gitlab.io/prtg-pyprobe/
Project-URL: Code, https://gitlab.com/paessler-labs/prtg-pyprobe
Project-URL: Issue tracker, https://gitlab.com/paessler-labs/prtg-pyprobe/-/issues
Platform: any
Classifier: Development Status :: 4 - Beta
Classifier: Intended Audience :: Developers
Classifier: Intended Audience :: System Administrators
Classifier: Framework :: AsyncIO
Classifier: License :: OSI Approved :: BSD License
Classifier: Operating System :: OS Independent
Classifier: Programming Language :: Python
Classifier: Topic :: System :: Monitoring
Classifier: Topic :: System :: Networking :: Monitoring
Requires-Python: >=3.7
License-File: LICENSE.txt
Requires-Dist: click
Requires-Dist: requests
Requires-Dist: PyInquirer
Requires-Dist: pythonping
Requires-Dist: pyyaml
Requires-Dist: certifi
Requires-Dist: cerberus
Requires-Dist: psutil
Requires-Dist: aiodns
Requires-Dist: cchardet
Requires-Dist: dnspython
Requires-Dist: pysnmp
Requires-Dist: aioping
Requires-Dist: httpx
Requires-Dist: python-daemon
Requires-Dist: backoff
Requires-Dist: aioboto3
Requires-Dist: dpath
Requires-Dist: prometheus-client
